xsoar_client/__about__.py
xsoar_client/__init__.py
xsoar_client/artifact_provider.py
xsoar_client/config.py
xsoar_client/xsoar_client.py
xsoar_client/artifact_providers/__init__.py
xsoar_client/artifact_providers/azure.py
xsoar_client/artifact_providers/base.py
xsoar_client/artifact_providers/s3.py
xsoar_client-2.0.1.dist-info/METADATA
xsoar_client-2.0.1.dist-info/WHEEL
xsoar_client-2.0.1.dist-info/licenses/LICENSE.txt
xsoar_client-2.0.1.dist-info/RECORD
