Metadata-Version: 2.4
Name: xsoar-client
Version: 2.0.1
Project-URL: Documentation, https://github.com/tlium/xsoar-client#readme
Project-URL: Issues, https://github.com/tlium/xsoar-client/issues
Project-URL: Source, https://github.com/tlium/xsoar-client
Author-email: Torbjørn Lium <torben@lium.org>
License-Expression: MIT
License-File: LICENSE.txt
Classifier: Development Status :: 4 - Beta
Classifier: Programming Language :: Python
Classifier: Programming Language :: Python :: 3.8
Classifier: Programming Language :: Python :: 3.9
Classifier: Programming Language :: Python :: 3.10
Classifier: Programming Language :: Python :: 3.11
Classifier: Programming Language :: Python :: 3.12
Requires-Python: >=3.10
Requires-Dist: azure-identity>=1.25.1
Requires-Dist: azure-storage-blob>=12.28.0
Requires-Dist: boto3>=1.36.17
Requires-Dist: demisto-py>=3.2.18
Requires-Dist: requests>=2.8.0
